README.md
setup.cfg
setup.py
R3C.egg-info/PKG-INFO
R3C.egg-info/SOURCES.txt
R3C.egg-info/dependency_links.txt
R3C.egg-info/entry_points.txt
R3C.egg-info/not-zip-safe
R3C.egg-info/requires.txt
R3C.egg-info/top_level.txt
bigchaindb/__init__.py
bigchaindb/config_utils.py
bigchaindb/core.py
bigchaindb/events.py
bigchaindb/exceptions.py
bigchaindb/fastquery.py
bigchaindb/lib.py
bigchaindb/log.py
bigchaindb/models.py
bigchaindb/parallel_validation.py
bigchaindb/start.py
bigchaindb/tendermint_utils.py
bigchaindb/utils.py
bigchaindb/validation.py
bigchaindb/version.py
bigchaindb/backend/__init__.py
bigchaindb/backend/connection.py
bigchaindb/backend/exceptions.py
bigchaindb/backend/query.py
bigchaindb/backend/schema.py
bigchaindb/backend/utils.py
bigchaindb/backend/localmongodb/__init__.py
bigchaindb/backend/localmongodb/connection.py
bigchaindb/backend/localmongodb/query.py
bigchaindb/backend/localmongodb/schema.py
bigchaindb/commands/__init__.py
bigchaindb/commands/bigchaindb.py
bigchaindb/commands/election_types.py
bigchaindb/commands/utils.py
bigchaindb/common/__init__.py
bigchaindb/common/crypto.py
bigchaindb/common/exceptions.py
bigchaindb/common/memoize.py
bigchaindb/common/transaction.py
bigchaindb/common/transaction_mode_types.py
bigchaindb/common/utils.py
bigchaindb/common/schema/__init__.py
bigchaindb/common/schema/transaction_chain_migration_election_v2.0.yaml
bigchaindb/common/schema/transaction_create_v1.0.yaml
bigchaindb/common/schema/transaction_create_v2.0.yaml
bigchaindb/common/schema/transaction_transfer_v1.0.yaml
bigchaindb/common/schema/transaction_transfer_v2.0.yaml
bigchaindb/common/schema/transaction_v1.0.yaml
bigchaindb/common/schema/transaction_v2.0.yaml
bigchaindb/common/schema/transaction_validator_election_v2.0.yaml
bigchaindb/common/schema/transaction_vote_v2.0.yaml
bigchaindb/elections/__init__.py
bigchaindb/elections/election.py
bigchaindb/elections/vote.py
bigchaindb/migrations/__init__.py
bigchaindb/migrations/chain_migration_election.py
bigchaindb/upsert_validator/__init__.py
bigchaindb/upsert_validator/validator_election.py
bigchaindb/upsert_validator/validator_utils.py
bigchaindb/web/__init__.py
bigchaindb/web/routes.py
